Metadata-Version: 2.1
Name: pyreducer
Version: 0.0.15
Summary: package for optimize common task 
Home-page: https://github.com/Mahath-M-U/pyreducer
Author: Mahath M U
Author-email: mahathmu@outlook.com
License: GNU GPL v3
Platform: UNKNOWN
